ai_cursor_init-0.3.0.dist-info/licenses/LICENSE
cursor_init/__init__.py
cursor_init/__main__.py
cursor_init/adr.py
cursor_init/ai_config.py
cursor_init/ai_service.py
cursor_init/ai_update_docs.py
cursor_init/check_docs.py
cursor_init/config.py
cursor_init/detect_framework.py
cursor_init/generate_diagrams.py
cursor_init/generate_docs.py
cursor_init/infer_diagrams.py
cursor_init/init_command.py
cursor_init/rfc.py
cursor_init/update_docs.py
ai_cursor_init-0.3.0.dist-info/METADATA
ai_cursor_init-0.3.0.dist-info/WHEEL
ai_cursor_init-0.3.0.dist-info/entry_points.txt
ai_cursor_init-0.3.0.dist-info/top_level.txt
ai_cursor_init-0.3.0.dist-info/RECORD
