Metadata-Version: 2.4
Name: ai-cursor-init
Version: 0.3.0
Summary: AI-powered documentation framework with intelligent code analysis, multi-provider AI support (OpenAI, Anthropic, Gemini), and context-aware generation of architecture docs, ADRs, and diagrams
Author-email: cursor-init contributors <e@mgiovani.com>
License-Expression: MIT
Project-URL: Homepage, https://github.com/mgiovani/ai-cursor-init
Project-URL: Repository, https://github.com/mgiovani/ai-cursor-init
Project-URL: Issues, https://github.com/mgiovani/ai-cursor-init/issues
Project-URL: Documentation, https://github.com/mgiovani/ai-cursor-init#readme
Keywords: documentation,adr,architecture,diagrams,cursor,ide,ai
Classifier: Development Status :: 4 - Beta
Classifier: Intended Audience :: Developers
Classifier: Operating System :: OS Independent
Classifier: Programming Language :: Python :: 3
Classifier: Programming Language :: Python :: 3.12
Classifier: Topic :: Documentation
Classifier: Topic :: Software Development :: Documentation
Classifier: Topic :: Text Processing :: Markup :: Markdown
Classifier: Topic :: Scientific/Engineering :: Artificial Intelligence
Classifier: Topic :: Software Development :: Code Generators
Requires-Python: >=3.12
License-File: LICENSE
Requires-Dist: PyYAML>=6.0
Requires-Dist: openai>=1.0.0
Requires-Dist: anthropic>=0.25.0
Requires-Dist: google-generativeai>=0.8.0
Requires-Dist: python-dotenv>=1.0.0
Requires-Dist: rich>=13.0.0
Requires-Dist: tiktoken>=0.6.0
Provides-Extra: dev
Requires-Dist: pytest>=7.0.0; extra == "dev"
Requires-Dist: pytest-cov>=4.0.0; extra == "dev"
Requires-Dist: black>=22.0.0; extra == "dev"
Requires-Dist: isort>=5.0.0; extra == "dev"
Requires-Dist: flake8>=5.0.0; extra == "dev"
Requires-Dist: mypy>=1.0.0; extra == "dev"
Requires-Dist: build>=0.10.0; extra == "dev"
Requires-Dist: twine>=4.0.0; extra == "dev"
Dynamic: license-file
